arsonist/Color.py
arsonist/__init__.py
arsonist/rip.py
arsonist/terminal.py
arsonist-0.0.1.dist-info/LICENSE
arsonist-0.0.1.dist-info/METADATA
arsonist-0.0.1.dist-info/WHEEL
arsonist-0.0.1.dist-info/top_level.txt
arsonist-0.0.1.dist-info/RECORD
